MANIFEST.in
setup.py
kolibri/__about__.py
kolibri/__about__.pyc
kolibri/__init__.py
kolibri/__init__.pyc
kolibri/cli.py
kolibri/cli.pyc
kolibri/kolibri.py
kolibri/kolibri.pyc
kolibri/mambo.pyc
kolibri/publisher.pyc
kolibri/utils.py
kolibri/utils.pyc
kolibri/yass.pyc
kolibri/extras/__init__.py
kolibri/extras/__init__.pyc
kolibri/extras/htmlcompress.py
kolibri/extras/htmlcompress.pyc
kolibri/extras/jade.pyc
kolibri/extras/macros.1.html
kolibri/extras/macros.html
kolibri/extras/md.py
kolibri/extras/md.pyc
kolibri/skel/README.md
kolibri/skel/kolibri.yml
kolibri/skel/content/hello-world.md
kolibri/skel/data/cars.json
kolibri/skel/pages/about.html
kolibri/skel/pages/advanced.html
kolibri/skel/pages/contact.html
kolibri/skel/pages/error.html
kolibri/skel/pages/index.html
kolibri/skel/plugins/default.py
kolibri/skel/static/main.css
kolibri/skel/static/main.js
kolibri/skel/static/images/kolibri.png
kolibri/skel/static/vendor/kolibri.css
kolibri/skel/static/vendor/milligram.css
kolibri/skel/static/vendor/normalize.css
kolibri/skel/templates/layouts/default.html
kolibri/skel/templates/layouts/footer.html
kolibri/skel/templates/layouts/header.html
kolibri/skel/templates/partials/my_table.html
kolibri_ssg.egg-info/PKG-INFO
kolibri_ssg.egg-info/SOURCES.txt
kolibri_ssg.egg-info/dependency_links.txt
kolibri_ssg.egg-info/entry_points.txt
kolibri_ssg.egg-info/not-zip-safe
kolibri_ssg.egg-info/requires.txt
kolibri_ssg.egg-info/top_level.txt